[
  {
    "公司名称": "西部金属材料股份有限公司",
    "英文名称": "Western Metal Materials Co., Ltd.",
    "曾用简称": null,
    "A股代码": "002149",
    "A股简称": "西部材料",
    "B股代码": null,
    "B股简称": null,
    "H股代码": null,
    "H股简称": null,
    "入选指数": "国证2000,国证Ａ指,深市精选,中小创新",
    "所属市场": "深交所主板",
    "所属行业": "有色金属冶炼和压延加工业",
    "法人代表": "杨延安",
    "注册资金": 48821.4274,
    "成立日期": "2000-12-28",
    "上市日期": "2007-08-10",
    "官方网站": "www.c-wmm.com",
    "电子邮箱": "002149@c-wmm.com",
    "联系电话": "029-86968418",
    "传真": "029-86968416",
    "注册地址": "陕西省西安市经开区泾渭工业园西金路西段15号",
    "办公地址": "陕西省西安市经开区泾渭工业园西金路西段15号",
    "邮政编码": "710201",
    "主营业务": "稀有金属材料的研发、生产和销售。",
    "经营范围": "一般项目：金属材料制造；金属结构制造；有色金属合金制造；有色金属铸造；有色金属压延加工；真空镀膜加工；金属切削加工服务；合成材料制造（不含危险化学品）；专用化学产品制造（不含危险化学品）；金属材料销售；金属结构销售；有色金属合金销售；新型金属功能材料销售；高性能有色金属及合金材料销售；铸造用造型材料销售；合成材料销售；专用化学产品销售（不含危险化学品）；新材料技术研发；金属制品研发；工程和技术研究和试验发展；技术服务、技术开发、技术咨询、技术交流、技术转让、技术推广；货物进出口；技术进出口；物业管理；土地使用权租赁；租赁服务（不含许可类租赁服务）；机械设备租赁；非居住房地产租赁。（除依法须经批准的项目外，凭营业执照依法自主开展经营活动）许可项目：危险化学品经营。（除依法须经批准的项目外，经相关部门批准后方可开展经营活动，具体经营项目以审批结果为准）",
    "机构简介": "西部金属材料股份有限公司原名西研稀有金属新材料股份有限公司，是2000年12月25日经陕西省人民政府《关于设立西研稀有金属新材料股份有限公司的批复》（陕政函[2000]313号）文件批准，由西北院作为主发起人，联合株洲硬质合金厂（于2002年整体改制为株洲硬质合金集团有限公司）、浙江省创业投资有限公司（于2005年更名为浙江省创业投资集团有限公司）、中国有色金属工业技术开发交流中心、九江有色金属冶炼厂，采用发起设立方式设立的股份有限公司。公司于2000年12月28日在陕西省工商行政管理局领取企业法人营业执照，营业执照号为：6100001011145。2002年8月13日，根据陕西省经济体制改革委员会办公室《关于同意西研稀有金属新材料股份有限公司增资扩股的批复》（陕改办发[2002]79号），并经公司2002年第一次临时股东大会批准，公司进行了增资扩股。增资扩股后，总股本由5342万股增加为6842万股。2003年公司更名为西部金属材料股份有限公司，并于2003年9月28日在陕西省工商行政管理局领取了变更名称后的企业法人营业执照。"
  }
]