[
  {
    "公司名称": "润泽智算科技集团股份有限公司",
    "英文名称": "Range Intelligent Computing Technology Group Company Limited",
    "曾用简称": "普丽盛",
    "A股代码": "300442",
    "A股简称": "润泽科技",
    "B股代码": null,
    "B股简称": null,
    "H股代码": null,
    "H股简称": null,
    "入选指数": "创业板50,创业板指,创业新兴,国证Ａ指,沪深300,巨潮中盘,深成指R,深证100,深证100R,深证300,深证成指,深证新兴,中创100",
    "所属市场": "深交所创业板",
    "所属行业": "软件和信息技术服务业",
    "法人代表": "周超男",
    "注册资金": 163434.3573,
    "成立日期": "2007-06-27",
    "上市日期": "2015-04-24",
    "官方网站": "www.cn-pls.com",
    "电子邮箱": "ir@rangeidc.com",
    "联系电话": "0316-6081283",
    "传真": "0316-6081283",
    "注册地址": "河北省廊坊开发区楼庄路9号1幢九层",
    "办公地址": "河北省廊坊经济技术开发区楼庄路9号",
    "邮政编码": "065001",
    "主营业务": "数据中心运营。",
    "经营范围": "许可项目：第一类增值电信业务；第二类增值电信业务；互联网信息服务；基础电信业务。（依法须经批准的项目，经相关部门批准后方可开展经营活动，具体经营项目以相关部门批准文件或许可证件为准）一般项目：人工智能行业应用系统集成服务；人工智能基础软件开发；人工智能公共服务平台技术咨询服务；数据处理和存储支持服务；技术服务、技术开发、技术咨询、技术交流、技术转让、技术推广；信息系统集成服务；信息技术咨询服务。（除依法须经批准的项目外，凭营业执照依法自主开展经营活动）",
    "机构简介": "普丽盛有限成立于2007年6月27日，由上海大容贸易有限公司、上海信维信息网络技术有限公司闵和上海闵行科技创业投资有限公司等3名股东出资设立，注册资本为2,000万元。股份公司系经上海市商务委员会出具的《市商务委关于同意上海普丽盛轻工设备有限公司改制为股份有限公司的批复》（沪商外资批[2011]2586号）和上海市人民政府出具的《中华人民共和国外商投资企业批准证书》（商外资沪股份字[2010]3300号）批准，由上海大容贸易有限公司、Masterwell (HK) Limited、软库博辰创业投资企业、苏州工业园区合杰创业投资中心（有限合伙）、SV Investments Company Limited等18名普丽盛有限全体股东作为发起人，以普丽盛有限截至2011年4月30日经立信会计师事务所有限公司审计的净资产折股整体变更设立的股份有限公司。公司于2011年9月27日取得上海工商局核发的《企业法人营业执照》（注册号：310228001027235），注册资本7,500万元。"
  }
]